{
	"name": "101_GR06_RAW_ADLS_Tweets",
	"properties": {
		"linkedServiceName": {
			"referenceName": "101_GR06_LS_ADLS_DATA",
			"type": "LinkedServiceReference"
		},
		"annotations": [],
		"type": "DelimitedText",
		"typeProperties": {
			"location": {
				"type": "AzureBlobFSLocation",
				"fileName": "Crypto_Tweets_Sentiment.csv",
				"folderPath": "101_GR06/RAW",
				"fileSystem": "dspdata"
			},
			"columnDelimiter": ",",
			"escapeChar": "\\",
			"firstRowAsHeader": true,
			"quoteChar": "\""
		},
		"schema": [
			{
				"name": "Prop_0",
				"type": "String"
			},
			{
				"name": "id",
				"type": "String"
			},
			{
				"name": "conversation_id",
				"type": "String"
			},
			{
				"name": "created_at",
				"type": "String"
			},
			{
				"name": "date",
				"type": "String"
			},
			{
				"name": "time",
				"type": "String"
			},
			{
				"name": "timezone",
				"type": "String"
			},
			{
				"name": "user_id",
				"type": "String"
			},
			{
				"name": "username",
				"type": "String"
			},
			{
				"name": "name",
				"type": "String"
			},
			{
				"name": "place",
				"type": "String"
			},
			{
				"name": "tweet",
				"type": "String"
			},
			{
				"name": "language",
				"type": "String"
			},
			{
				"name": "mentions",
				"type": "String"
			},
			{
				"name": "urls",
				"type": "String"
			},
			{
				"name": "photos",
				"type": "String"
			},
			{
				"name": "replies_count",
				"type": "String"
			},
			{
				"name": "retweets_count",
				"type": "String"
			},
			{
				"name": "likes_count",
				"type": "String"
			},
			{
				"name": "hashtags",
				"type": "String"
			},
			{
				"name": "cashtags",
				"type": "String"
			},
			{
				"name": "link",
				"type": "String"
			},
			{
				"name": "retweet",
				"type": "String"
			},
			{
				"name": "quote_url",
				"type": "String"
			},
			{
				"name": "video",
				"type": "String"
			},
			{
				"name": "thumbnail",
				"type": "String"
			},
			{
				"name": "near",
				"type": "String"
			},
			{
				"name": "geo",
				"type": "String"
			},
			{
				"name": "source",
				"type": "String"
			},
			{
				"name": "user_rt_id",
				"type": "String"
			},
			{
				"name": "user_rt",
				"type": "String"
			},
			{
				"name": "retweet_id",
				"type": "String"
			},
			{
				"name": "reply_to",
				"type": "String"
			},
			{
				"name": "retweet_date",
				"type": "String"
			},
			{
				"name": "translate",
				"type": "String"
			},
			{
				"name": "trans_src",
				"type": "String"
			},
			{
				"name": "trans_dest",
				"type": "String"
			},
			{
				"name": "search",
				"type": "String"
			},
			{
				"name": "decoded_tweet",
				"type": "String"
			},
			{
				"name": "neg",
				"type": "String"
			},
			{
				"name": "neu",
				"type": "String"
			},
			{
				"name": "pos",
				"type": "String"
			},
			{
				"name": "compound",
				"type": "String"
			}
		]
	},
	"type": "Microsoft.DataFactory/factories/datasets"
}